lbsolver/__init__.py
lbsolver/lbsolver.py
lbsolver-1.0.0.dist-info/LICENSE
lbsolver-1.0.0.dist-info/METADATA
lbsolver-1.0.0.dist-info/WHEEL
lbsolver-1.0.0.dist-info/entry_points.txt
lbsolver-1.0.0.dist-info/top_level.txt
lbsolver-1.0.0.dist-info/RECORD
