Metadata-Version: 2.1
Name: lbsolver
Version: 1.0.0
Summary: A package containing a solver for the NYT Letter Boxed Game
Author: Derik Pack
License: MIT License
Project-URL: Homepage, https://github.com/packdl/letter-boxed-solver
Project-URL: API Documentation, https://packdl.github.io/letter-boxed-solver/
Classifier: Programming Language :: Python :: 3
Classifier: License :: OSI Approved :: MIT License
Classifier: Development Status :: 4 - Beta
Requires-Python: >=3.9
License-File: LICENSE
Provides-Extra: dev
Requires-Dist: black ; extra == 'dev'
Requires-Dist: coverage ; extra == 'dev'
Requires-Dist: pytest ; extra == 'dev'
Requires-Dist: sphinx ; extra == 'dev'
Requires-Dist: myst-parser ; extra == 'dev'
